XInput.py
XInput_Python-0.4.0.dist-info/LICENSE
XInput_Python-0.4.0.dist-info/METADATA
XInput_Python-0.4.0.dist-info/WHEEL
XInput_Python-0.4.0.dist-info/top_level.txt
XInput_Python-0.4.0.dist-info/RECORD
