Metadata-Version: 2.1
Name: XInput-Python
Version: 0.4.0
Summary: A simple to use interface to the XInput API for Python
Home-page: https://github.com/Zuzu-Typ/XInput-Python
Author: Zuzu_Typ
Author-email: zuzu.typ@gmail.com
License: zlib/libpng license
Keywords: XInput xinput-controller xinput-wrapper directx controller controller-api wrapper windows thread threaded async
Platform: UNKNOWN
Classifier: Development Status :: 3 - Alpha
Classifier: Intended Audience :: Developers
Classifier: Topic :: Games/Entertainment
Classifier: Topic :: Software Development :: Libraries
Classifier: License :: OSI Approved :: zlib/libpng License
Classifier: Programming Language :: Python :: 2
Classifier: Programming Language :: Python :: 2.7
Classifier: Programming Language :: Python :: 3
Classifier: Programming Language :: Python :: 3.3
Classifier: Programming Language :: Python :: 3.4
Classifier: Programming Language :: Python :: 3.5
Classifier: Programming Language :: Python :: 3.6
Classifier: Programming Language :: Python :: 3.7
